philander/.gitignore
philander/__init__.py
philander/accelerometer.py
philander/actuator.py
philander/adc.py
philander/adc_micropython.py
philander/adc_sim.py
philander/battery.py
philander/bma456.py
philander/bma456_feat_an.dat
philander/bma456_feat_hbl.dat
philander/bma456_feat_mm.dat
philander/bma456_feat_wbl.dat
philander/bma456_reg.py
philander/button.py
philander/charger.py
philander/configurable.py
philander/dictionary.py
philander/gasgauge.py
philander/gpio.py
philander/gpio_micropython.py
philander/gpio_periphery.py
philander/gpio_rpi.py
philander/gpio_sim.py
philander/gpio_zero.py
philander/htu21d.py
philander/hygrometer.py
philander/imath.py
philander/interruptable.py
philander/l6924.py
philander/led.py
philander/max77960.py
philander/max77960_reg.py
philander/mcp40.py
philander/module.py
philander/penum.py
philander/potentiometer.py
philander/primitives.py
philander/pwm.py
philander/pwm_micropython.py
philander/pwm_periphery.py
philander/pwm_rpi.py
philander/sensor.py
philander/serialbus.py
philander/serialbus_micropython.py
philander/serialbus_periphery.py
philander/serialbus_sim.py
philander/serialbus_smbus2.py
philander/simBMA456.py
philander/simdev.py
philander/stadc1283.py
philander/stc3115.py
philander/stc3115_reg.py
philander/stc3117.py
philander/stc3117_reg.py
philander/stc311x.py
philander/stc311x_reg.py
philander/sysfactory.py
philander/systypes.py
philander/thermometer.py
philander/vibrasense.py
philander/vibrasense2.py
philander/voltmeter.py
philander/watchdog.py
philander-0.5.1.dist-info/METADATA
philander-0.5.1.dist-info/WHEEL
philander-0.5.1.dist-info/licenses/LICENSE.txt
philander-0.5.1.dist-info/RECORD
