Metadata-Version: 2.4
Name: philander
Version: 0.5.1
Summary: Driver collection for embedded systems or wireless sensor nodes.
Project-URL: Homepage, https://github.com/olimaye/philander
Project-URL: Documentation, http://philander.readthedocs.io
Project-URL: Bug Tracker, https://github.com/olimaye/philander/issues
Project-URL: Changelog, https://github.com/olimaye/philander/blob/master/changelog.md
Author: Oliver Maye
Author-email: maye@ihp-microelectronics.com
License: EUPL-1.2
License-File: LICENSE.txt
Keywords: WSN,accelerometer,driver,hardware abstraction,platform,sensor
Classifier: Development Status :: 6 - Mature
Classifier: Environment :: Console
Classifier: Environment :: No Input/Output (Daemon)
Classifier: Environment :: Other Environment
Classifier: Intended Audience :: Developers
Classifier: Intended Audience :: Education
Classifier: Intended Audience :: Science/Research
Classifier: License :: OSI Approved :: European Union Public Licence 1.2 (EUPL 1.2)
Classifier: Operating System :: OS Independent
Classifier: Programming Language :: Python :: 3 :: Only
Classifier: Programming Language :: Python :: 3.4
Classifier: Programming Language :: Python :: Implementation :: CPython
Classifier: Programming Language :: Python :: Implementation :: MicroPython
Classifier: Topic :: Software Development :: Embedded Systems
Classifier: Topic :: Software Development :: Libraries :: Application Frameworks
Classifier: Topic :: Software Development :: Libraries :: Python Modules
Classifier: Topic :: System :: Hardware :: Hardware Drivers
Requires-Python: >=3.4
Requires-Dist: argparse; implementation_name == 'micropython'
Requires-Dist: gpiozero; platform_machine == 'aarch64'
Requires-Dist: logging; implementation_name == 'micropython'
Requires-Dist: pymitter
Requires-Dist: smbus2; platform_machine == 'aarch64'
Requires-Dist: threading; implementation_name == 'micropython'
Requires-Dist: unittest; implementation_name == 'micropython'
Requires-Dist: warnings; implementation_name == 'micropython'
